alert_after_pro/__init__.py
alert_after_pro/config.py
alert_after_pro/main.py
alert_after_pro/utils.py
alert_after_pro/notifiers/__init__.py
alert_after_pro/notifiers/base.py
alert_after_pro/notifiers/dingding.py
alert_after_pro/notifiers/ntfy.py
alert_after_pro/notifiers/pushover.py
alert_after_pro/notifiers/sms.py
alert_after_pro/notifiers/telegram.py
alert_after_pro-0.2.2.dist-info/licenses/LICENSE
alert_after_pro-0.2.2.dist-info/METADATA
alert_after_pro-0.2.2.dist-info/WHEEL
alert_after_pro-0.2.2.dist-info/entry_points.txt
alert_after_pro-0.2.2.dist-info/top_level.txt
alert_after_pro-0.2.2.dist-info/RECORD
