Metadata-Version: 2.4
Name: alert-after-pro
Version: 0.2.2
Summary: Get notified when your commands complete - supports Telegram, SMS, DingDing, Ntfy, and more
Home-page: https://github.com/MatrixA/alert-after-pro
Author: Alert After Pro Team
Author-email: alert@afterpro.dev
Project-URL: Bug Reports, https://github.com/MatrixA/alert-after-pro/issues
Project-URL: Source, https://github.com/MatrixA/alert-after-pro
Keywords: notification alert command monitoring telegram sms dingding ntfy
Classifier: Development Status :: 4 - Beta
Classifier: Intended Audience :: Developers
Classifier: Intended Audience :: System Administrators
Classifier: License :: OSI Approved :: MIT License
Classifier: Operating System :: OS Independent
Classifier: Programming Language :: Python :: 3
Classifier: Programming Language :: Python :: 3.7
Classifier: Programming Language :: Python :: 3.8
Classifier: Programming Language :: Python :: 3.9
Classifier: Programming Language :: Python :: 3.10
Classifier: Programming Language :: Python :: 3.11
Classifier: Topic :: System :: Monitoring
Classifier: Topic :: System :: Systems Administration
Classifier: Topic :: Utilities
Requires-Python: >=3.7
License-File: LICENSE
Requires-Dist: requests>=2.25.0
Requires-Dist: PyYAML>=5.4.0
Provides-Extra: sms
Requires-Dist: twilio>=7.0.0; extra == "sms"
Provides-Extra: all
Requires-Dist: twilio>=7.0.0; extra == "all"
Provides-Extra: dev
Requires-Dist: pytest>=6.0; extra == "dev"
Requires-Dist: pytest-cov>=2.0; extra == "dev"
Requires-Dist: black>=21.0; extra == "dev"
Requires-Dist: flake8>=3.8; extra == "dev"
Dynamic: author
Dynamic: author-email
Dynamic: classifier
Dynamic: description
Dynamic: description-content-type
Dynamic: home-page
Dynamic: keywords
Dynamic: license-file
Dynamic: project-url
Dynamic: provides-extra
Dynamic: requires-dist
Dynamic: requires-python
Dynamic: summary
